spotify2youtubemusic/download.py
spotify2youtubemusic/send.py
spotify2youtubemusic-0.1.2.dist-info/METADATA
spotify2youtubemusic-0.1.2.dist-info/WHEEL
spotify2youtubemusic-0.1.2.dist-info/top_level.txt
spotify2youtubemusic-0.1.2.dist-info/RECORD
