Metadata-Version: 2.1
Name: spotify2youtubemusic
Version: 0.1.2
Requires-Dist: requests
